LICENSE
MANIFEST.in
README.rst
config.ini
setup.py
hlsclient/__init__.py
hlsclient/__main__.py
hlsclient/atomic.py
hlsclient/balancer.py
hlsclient/cleaner.py
hlsclient/combine.py
hlsclient/consumer.py
hlsclient/crypto.py
hlsclient/discover.py
hlsclient/helpers.py
hlsclient/lock.py
hlsclient/pkcs7.py
hlsclient/transcode.py
hlsclient.egg-info/PKG-INFO
hlsclient.egg-info/SOURCES.txt
hlsclient.egg-info/dependency_links.txt
hlsclient.egg-info/not-zip-safe
hlsclient.egg-info/requires.txt
hlsclient.egg-info/top_level.txt