Metadata-Version: 1.0
Name: hlsclient
Version: 0.4.7
Summary: Client to download all files from HLS streams
Home-page: https://github.com/globocom/hlsclient
Author: Globo.com
Author-email: UNKNOWN
License: UNKNOWN
Platform: UNKNOWN
